tabby_connection_gateway/__init__.py
tabby_connection_gateway/admin_server.py
tabby_connection_gateway/base.py
tabby_connection_gateway/cli.py
tabby_connection_gateway/gateway_server.py
tabby_connection_gateway-0.1.3.dist-info/LICENSE
tabby_connection_gateway-0.1.3.dist-info/METADATA
tabby_connection_gateway-0.1.3.dist-info/WHEEL
tabby_connection_gateway-0.1.3.dist-info/entry_points.txt
tabby_connection_gateway-0.1.3.dist-info/top_level.txt
tabby_connection_gateway-0.1.3.dist-info/RECORD
