Metadata-Version: 2.1
Name: tabby-connection-gateway
Version: 0.1.3
Summary: Python Boilerplate contains all the boilerplate you need to create a Python package.
Home-page: https://github.com/eugeny/tabby_connection_gateway
Author: Eugene Pankov
Author-email: e@ajenti.org
License: MIT license
Keywords: tabby_connection_gateway
Platform: UNKNOWN
Classifier: Development Status :: 2 - Pre-Alpha
Classifier: License :: OSI Approved :: MIT License
Classifier: Natural Language :: English
Classifier: Programming Language :: Python :: 3
Classifier: Programming Language :: Python :: 3.6
Classifier: Programming Language :: Python :: 3.7
Classifier: Programming Language :: Python :: 3.8
Requires-Python: >=3.6
License-File: LICENSE
Requires-Dist: websockets (>=9.1)
